{
    "subjectName": "mrecentupdates",
    "lectures": [
        {
            "title": "Surgery recent updates - Bailey Chapters 1 to 5",
            "streamingUrl": "https://web.afrahtafreeh.site/prepare/D42uVlLD_AuSqWRkam-Hng"
        },
        {
            "title": "Surgery Recent updates - Nutriton",
            "streamingUrl": "https://web.afrahtafreeh.site/prepare/HrAkGyitHlE-OvzWSLXT5A"
        },
        {
            "title": "Surgery Recent updates -Trauma",
            "streamingUrl": "https://web.afrahtafreeh.site/prepare/Wy56fC1fpEkF1Lhb4UCwgw"
        },
        {
            "title": "Surgery Recent updates - Endocrine Surgery",
            "streamingUrl": "https://web.afrahtafreeh.site/prepare/2tYbhWq21u_3AKRmDB3CAg"
        },
        {
            "title": "Surgery Recent updates - Head and Neck section",
            "streamingUrl": "https://web.afrahtafreeh.site/prepare/lB2VkOFhCUCOlHFhR8SXSw"
        },
        {
            "title": "Surgery Recent updates - GIT Part 1",
            "streamingUrl": "https://web.afrahtafreeh.site/prepare/mayhTN642N69M8UXd2Vg1A"
        },
        {
            "title": "Surgery Recent updates - GIT Part 2",
            "streamingUrl": "https://web.afrahtafreeh.site/prepare/uY5GJgBwuBkC08ikHLeG1w"
        },
        {
            "title": "Surgery Recent updates - GIT Part 3",
            "streamingUrl": "https://web.afrahtafreeh.site/prepare/Oja2l3SkcqbnLPwseDNFmQ"
        },
        {
            "title": "Surgery Recent updates - Urology",
            "streamingUrl": "https://web.afrahtafreeh.site/prepare/qt9n-9Kg5flRJ1jelkdE0A"
        },
        {
            "title": "Surgery Recent updates - Transplant surgery",
            "streamingUrl": "https://web.afrahtafreeh.site/prepare/zwhc0oYJbCO5qkXUzTeYmg"
        },
        {
            "title": "Surgery Recent updates - Vascular surgery",
            "streamingUrl": "https://web.afrahtafreeh.site/prepare/Paye7jMbzrscZq2wLd-xdQ"
        },
        {
            "title": "Surgery Recent updates - Pediatrics surgery",
            "streamingUrl": "https://web.afrahtafreeh.site/prepare/WlNgaFMYPR6sny2OPrnCnQ"
        },
        {
            "title": "Medicine Recent updates - 1",
            "streamingUrl": "https://web.afrahtafreeh.site/prepare/Qg6bLcBTu34--MNGmvPs7A"
        },
        {
            "title": "Medicine Recent updates - 2",
            "streamingUrl": "https://web.afrahtafreeh.site/prepare/JAuPp_b-sTpPnEIMoUD5MA"
        },
        {
            "title": "OBGY Recent updates - 1",
            "streamingUrl": "https://web.afrahtafreeh.site/prepare/rFie0kZm6NIGzOwStZia-w"
        },
        {
            "title": "OBGY Recent updates - 2",
            "streamingUrl": "https://web.afrahtafreeh.site/prepare/9G-lqz8omxEiniuC9q1jBQ"
        },
        {
            "title": "Paediatrics Recent updates",
            "streamingUrl": "https://web.afrahtafreeh.site/prepare/rXBPqaG6gDgDuh_QC7uSbg"
        },
        {
            "title": "Dermatology Recent updates",
            "streamingUrl": "https://web.afrahtafreeh.site/prepare/AkiJ7G85V9T2yi0EkjBSFw"
        },
        {
            "title": "Community Medicine Recent updates -1",
            "streamingUrl": "https://web.afrahtafreeh.site/prepare/IPph5Wc8TBObFszj7Bzjxw"
        },
        {
            "title": "Community Medicine Recent updates -2",
            "streamingUrl": "https://web.afrahtafreeh.site/prepare/9foCa10DtXA8a-5IBcaPIw"
        },
        {
            "title": "Pharmacology Recent updates",
            "streamingUrl": "https://web.afrahtafreeh.site/prepare/_g52xofOnCEfaXT8B5r_dg"
        }
    ],
    "skipped": []
}